openexr_python/__init__.py
openexr_python/exr_header.py
openexr_python/exr_input_file.py
openexr_python/exr_output_file.py
openexr_python/util.py
openexr_python-2024.1.5.11.15.26.dist-info/LICENSE
openexr_python-2024.1.5.11.15.26.dist-info/METADATA
openexr_python-2024.1.5.11.15.26.dist-info/WHEEL
openexr_python-2024.1.5.11.15.26.dist-info/top_level.txt
openexr_python-2024.1.5.11.15.26.dist-info/RECORD
