Metadata-Version: 2.1
Name: openexr-python
Version: 2024.1.5.11.15.26
Summary: # OpenEXR-Python
Author-email: 404Vector <tiryul@gmail.com>
License: MIT License
Project-URL: Home, https://github.com/404Vector/OpenEXR-Python
Classifier: License :: OSI Approved :: MIT License
Requires-Python: >=3.9
License-File: LICENSE
Requires-Dist: openexr ==1.3.8
Requires-Dist: numpy
